[
  {
    "Id": 10001,
    "Name": "廉颇-技能1-伤害",
    "EffectType": 1,
    "BaseDamage": 200,
    "DamageType": 1,
    "AttackRatio": 0.5,
    "TargetPolicy": 1,
    "Radius": 0
  },
  {
    "Id": 10002,
    "Name": "廉颇-技能2-伤害",
    "EffectType": 1,
    "BaseDamage": 300,
    "DamageType": 1,
    "AttackRatio": 0.6,
    "TargetPolicy": 1,
    "Radius": 0
  },
  {
    "Id": 10003,
    "Name": "廉颇-技能3-伤害",
    "EffectType": 1,
    "BaseDamage": 400,
    "DamageType": 1,
    "AttackRatio": 0.8,
    "TargetPolicy": 2,
    "Radius": 5
  },
  {
    "Id": 100001,
    "Name": "Buff添加效果-日志",
    "EffectType": 1,
    "BaseDamage": 0,
    "DamageType": 1,
    "AttackRatio": 0,
    "TargetPolicy": 0,
    "Radius": 0
  },
  {
    "Id": 10101,
    "Name": "持续掉血效果",
    "EffectType": 1,
    "BaseDamage": 10,
    "DamageType": 1,
    "AttackRatio": 0,
    "TargetPolicy": 1,
    "Radius": 0
  },
  {
    "Id": 10010000,
    "Name": "廉颇-勇士之魂-添加霸体战意状态",
    "EffectType": 0,
    "BaseDamage": 0,
    "DamageType": 1,
    "AttackRatio": 0,
    "TargetPolicy": 0,
    "Radius": 0
  },
  {
    "Id": 10010101,
    "Name": "廉颇-爆裂冲撞-冲锋位移与碰撞判定",
    "EffectType": 0,
    "BaseDamage": 0,
    "DamageType": 1,
    "AttackRatio": 0,
    "TargetPolicy": 0,
    "Radius": 0
  },
  {
    "Id": 10010111,
    "Name": "廉颇-爆裂冲撞-命中伤害",
    "EffectType": 1,
    "BaseDamage": 160,
    "DamageType": 1,
    "AttackRatio": 0.6,
    "TargetPolicy": 1,
    "Radius": 0
  },
  {
    "Id": 10010201,
    "Name": "廉颇-熔岩重击-护盾与蓄力区域",
    "EffectType": 0,
    "BaseDamage": 0,
    "DamageType": 1,
    "AttackRatio": 0,
    "TargetPolicy": 0,
    "Radius": 3.5
  },
  {
    "Id": 10010211,
    "Name": "廉颇-熔岩重击-区域伤害",
    "EffectType": 1,
    "BaseDamage": 180,
    "DamageType": 1,
    "AttackRatio": 0.7,
    "TargetPolicy": 2,
    "Radius": 3.5
  },
  {
    "Id": 10010301,
    "Name": "廉颇-天崩地裂-第一段区域",
    "EffectType": 0,
    "BaseDamage": 0,
    "DamageType": 1,
    "AttackRatio": 0,
    "TargetPolicy": 0,
    "Radius": 4.5
  },
  {
    "Id": 10010311,
    "Name": "廉颇-天崩地裂-第二段区域",
    "EffectType": 0,
    "BaseDamage": 0,
    "DamageType": 1,
    "AttackRatio": 0,
    "TargetPolicy": 0,
    "Radius": 4.5
  },
  {
    "Id": 10010321,
    "Name": "廉颇-天崩地裂-第三段区域",
    "EffectType": 0,
    "BaseDamage": 0,
    "DamageType": 1,
    "AttackRatio": 0,
    "TargetPolicy": 0,
    "Radius": 4.5
  },
  {
    "Id": 10010331,
    "Name": "廉颇-天崩地裂-段落伤害",
    "EffectType": 1,
    "BaseDamage": 150,
    "DamageType": 1,
    "AttackRatio": 0.55,
    "TargetPolicy": 2,
    "Radius": 4.5
  },
  {
    "Id": 10010341,
    "Name": "廉颇-天崩地裂-第三段击飞",
    "EffectType": 0,
    "BaseDamage": 0,
    "DamageType": 1,
    "AttackRatio": 0,
    "TargetPolicy": 2,
    "Radius": 4.5
  },
  {
    "Id": 10020101,
    "Name": "小乔-绽放之舞-发射扇子",
    "EffectType": 0,
    "BaseDamage": 0,
    "DamageType": 2,
    "AttackRatio": 0,
    "TargetPolicy": 0,
    "Radius": 0
  },
  {
    "Id": 10020111,
    "Name": "小乔-绽放之舞-命中伤害",
    "EffectType": 1,
    "BaseDamage": 500,
    "DamageType": 2,
    "AttackRatio": 0.8,
    "TargetPolicy": 1,
    "Radius": 0
  },
  {
    "Id": 10020201,
    "Name": "小乔-甜蜜恋风-区域生成",
    "EffectType": 0,
    "BaseDamage": 0,
    "DamageType": 2,
    "AttackRatio": 0,
    "TargetPolicy": 0,
    "Radius": 4
  },
  {
    "Id": 10020211,
    "Name": "小乔-甜蜜恋风-区域命中伤害",
    "EffectType": 1,
    "BaseDamage": 100,
    "DamageType": 2,
    "AttackRatio": 0.45,
    "TargetPolicy": 2,
    "Radius": 4
  },
  {
    "Id": 10020301,
    "Name": "小乔-星华缭乱-添加持续状态",
    "EffectType": 0,
    "BaseDamage": 0,
    "DamageType": 2,
    "AttackRatio": 0,
    "TargetPolicy": 0,
    "Radius": 8
  },
  {
    "Id": 10020311,
    "Name": "小乔-星华缭乱-周期落星伤害",
    "EffectType": 1,
    "BaseDamage": 80,
    "DamageType": 2,
    "AttackRatio": 0.35,
    "TargetPolicy": 2,
    "Radius": 8
  },
  {
    "Id": 10030000,
    "Name": "赵云-龙鸣-被动强化普攻状态",
    "EffectType": 0,
    "BaseDamage": 0,
    "DamageType": 1,
    "AttackRatio": 0,
    "TargetPolicy": 0,
    "Radius": 0
  },
  {
    "Id": 10030101,
    "Name": "赵云-惊雷之龙-冲锋位移与碰撞判定",
    "EffectType": 0,
    "BaseDamage": 0,
    "DamageType": 1,
    "AttackRatio": 0,
    "TargetPolicy": 0,
    "Radius": 0
  },
  {
    "Id": 10030111,
    "Name": "赵云-惊雷之龙-命中伤害",
    "EffectType": 1,
    "BaseDamage": 150,
    "DamageType": 1,
    "AttackRatio": 0.65,
    "TargetPolicy": 1,
    "Radius": 0
  },
  {
    "Id": 10030201,
    "Name": "赵云-破云之龙-前方突刺区域",
    "EffectType": 0,
    "BaseDamage": 0,
    "DamageType": 1,
    "AttackRatio": 0,
    "TargetPolicy": 0,
    "Radius": 3.5
  },
  {
    "Id": 10030211,
    "Name": "赵云-破云之龙-突刺命中伤害",
    "EffectType": 1,
    "BaseDamage": 180,
    "DamageType": 1,
    "AttackRatio": 0.70,
    "TargetPolicy": 2,
    "Radius": 3.5
  },
  {
    "Id": 10030301,
    "Name": "赵云-天翔之龙-跳跃落地区域",
    "EffectType": 0,
    "BaseDamage": 0,
    "DamageType": 1,
    "AttackRatio": 0,
    "TargetPolicy": 0,
    "Radius": 4.5
  },
  {
    "Id": 10030311,
    "Name": "赵云-天翔之龙-落地伤害",
    "EffectType": 1,
    "BaseDamage": 250,
    "DamageType": 1,
    "AttackRatio": 0.90,
    "TargetPolicy": 2,
    "Radius": 4.5
  },
  {
    "Id": 10030102,
    "Name": "赵云-惊雷之龙-二档追加冲锋",
    "EffectType": 0,
    "BaseDamage": 0,
    "DamageType": 1,
    "AttackRatio": 0,
    "TargetPolicy": 0,
    "Radius": 0
  },
  {
    "Id": 10030103,
    "Name": "赵云-惊雷之龙-三档追加冲锋",
    "EffectType": 0,
    "BaseDamage": 0,
    "DamageType": 1,
    "AttackRatio": 0,
    "TargetPolicy": 0,
    "Radius": 0
  },
  {
    "Id": 10030202,
    "Name": "赵云-破云之龙-二档增强区域",
    "EffectType": 0,
    "BaseDamage": 0,
    "DamageType": 1,
    "AttackRatio": 0,
    "TargetPolicy": 0,
    "Radius": 4.5
  },
  {
    "Id": 10030203,
    "Name": "赵云-破云之龙-三档增强区域",
    "EffectType": 0,
    "BaseDamage": 0,
    "DamageType": 1,
    "AttackRatio": 0,
    "TargetPolicy": 0,
    "Radius": 5.5
  },
  {
    "Id": 10030212,
    "Name": "赵云-破云之龙-二档增强命中伤害",
    "EffectType": 1,
    "BaseDamage": 220,
    "DamageType": 1,
    "AttackRatio": 0.80,
    "TargetPolicy": 2,
    "Radius": 4.5
  },
  {
    "Id": 10030213,
    "Name": "赵云-破云之龙-三档增强命中伤害",
    "EffectType": 1,
    "BaseDamage": 260,
    "DamageType": 1,
    "AttackRatio": 0.90,
    "TargetPolicy": 2,
    "Radius": 5.5
  },
  {
    "Id": 10030302,
    "Name": "赵云-天翔之龙-三档增强落地区域",
    "EffectType": 0,
    "BaseDamage": 0,
    "DamageType": 1,
    "AttackRatio": 0,
    "TargetPolicy": 0,
    "Radius": 5.5
  },
  {
    "Id": 10030313,
    "Name": "赵云-天翔之龙-三档增强落地伤害",
    "EffectType": 1,
    "BaseDamage": 350,
    "DamageType": 1,
    "AttackRatio": 1.10,
    "TargetPolicy": 2,
    "Radius": 5.5
  },
  {
    "Id": 10030321,
    "Name": "赵云-天翔之龙-落地击飞",
    "EffectType": 0,
    "BaseDamage": 0,
    "DamageType": 1,
    "AttackRatio": 0,
    "TargetPolicy": 2,
    "Radius": 4.5
  },
  {
    "Id": 10040000,
    "Name": "墨子-机关术-被动护盾触发",
    "EffectType": 0,
    "BaseDamage": 0,
    "DamageType": 2,
    "AttackRatio": 0,
    "TargetPolicy": 0,
    "Radius": 0
  },
  {
    "Id": 10040101,
    "Name": "墨子-和平漫步-机甲突进与护盾",
    "EffectType": 0,
    "BaseDamage": 0,
    "DamageType": 2,
    "AttackRatio": 0,
    "TargetPolicy": 0,
    "Radius": 0
  },
  {
    "Id": 10040111,
    "Name": "墨子-和平漫步-突进命中伤害",
    "EffectType": 1,
    "BaseDamage": 200,
    "DamageType": 2,
    "AttackRatio": 0.60,
    "TargetPolicy": 1,
    "Radius": 0
  },
  {
    "Id": 10040201,
    "Name": "墨子-机关重炮-发射炮弹",
    "EffectType": 0,
    "BaseDamage": 0,
    "DamageType": 2,
    "AttackRatio": 0,
    "TargetPolicy": 0,
    "Radius": 0
  },
  {
    "Id": 10040211,
    "Name": "墨子-机关重炮-炮弹命中伤害",
    "EffectType": 1,
    "BaseDamage": 300,
    "DamageType": 2,
    "AttackRatio": 0.70,
    "TargetPolicy": 1,
    "Radius": 0
  },
  {
    "Id": 10040301,
    "Name": "墨子-墨守成规-展开机关屏障",
    "EffectType": 0,
    "BaseDamage": 0,
    "DamageType": 2,
    "AttackRatio": 0,
    "TargetPolicy": 0,
    "Radius": 5.0
  },
  {
    "Id": 10040311,
    "Name": "墨子-墨守成规-屏障周期伤害",
    "EffectType": 1,
    "BaseDamage": 120,
    "DamageType": 2,
    "AttackRatio": 0.35,
    "TargetPolicy": 2,
    "Radius": 5.0
  },
  {
    "Id": 10050000,
    "Name": "妲己-失心-降低法术防御",
    "EffectType": 0,
    "BaseDamage": 0,
    "DamageType": 2,
    "AttackRatio": 0,
    "TargetPolicy": 1,
    "Radius": 0
  },
  {
    "Id": 10050101,
    "Name": "妲己-灵魂冲击-发射冲击波",
    "EffectType": 0,
    "BaseDamage": 0,
    "DamageType": 2,
    "AttackRatio": 0,
    "TargetPolicy": 0,
    "Radius": 0
  },
  {
    "Id": 10050111,
    "Name": "妲己-灵魂冲击-命中伤害",
    "EffectType": 1,
    "BaseDamage": 520,
    "DamageType": 2,
    "AttackRatio": 0.8,
    "TargetPolicy": 1,
    "Radius": 0
  },
  {
    "Id": 10050201,
    "Name": "妲己-偶像魅力-目标点魅惑区域",
    "EffectType": 0,
    "BaseDamage": 0,
    "DamageType": 2,
    "AttackRatio": 0,
    "TargetPolicy": 0,
    "Radius": 3.0
  },
  {
    "Id": 10050211,
    "Name": "妲己-偶像魅力-伤害与眩晕",
    "EffectType": 1,
    "BaseDamage": 285,
    "DamageType": 2,
    "AttackRatio": 0.66,
    "TargetPolicy": 2,
    "Radius": 3.0
  },
  {
    "Id": 10050301,
    "Name": "妲己-女王崇拜-添加狐火状态",
    "EffectType": 0,
    "BaseDamage": 0,
    "DamageType": 2,
    "AttackRatio": 0,
    "TargetPolicy": 0,
    "Radius": 8.0
  },
  {
    "Id": 10050311,
    "Name": "妲己-女王崇拜-周期搜敌狐火",
    "EffectType": 0,
    "BaseDamage": 0,
    "DamageType": 2,
    "AttackRatio": 0,
    "TargetPolicy": 2,
    "Radius": 8.0
  },
  {
    "Id": 10050313,
    "Name": "妲己-女王崇拜-狐火命中伤害",
    "EffectType": 1,
    "BaseDamage": 325,
    "DamageType": 2,
    "AttackRatio": 0.75,
    "TargetPolicy": 1,
    "Radius": 0
  },
  {
    "Id": 10060000,
    "Name": "嬴政-王者审判-被动入口",
    "EffectType": 0,
    "BaseDamage": 0,
    "DamageType": 2,
    "AttackRatio": 0,
    "TargetPolicy": 0,
    "Radius": 0
  },
  {
    "Id": 10060101,
    "Name": "嬴政-王者惩戒-目标点剑阵",
    "EffectType": 0,
    "BaseDamage": 0,
    "DamageType": 2,
    "AttackRatio": 0,
    "TargetPolicy": 0,
    "Radius": 4.0
  },
  {
    "Id": 10060111,
    "Name": "嬴政-王者惩戒-剑阵伤害与减速",
    "EffectType": 1,
    "BaseDamage": 220,
    "DamageType": 2,
    "AttackRatio": 0.27,
    "TargetPolicy": 2,
    "Radius": 4.0
  },
  {
    "Id": 10060201,
    "Name": "嬴政-王者守御-净化护盾加速",
    "EffectType": 0,
    "BaseDamage": 0,
    "DamageType": 2,
    "AttackRatio": 0,
    "TargetPolicy": 0,
    "Radius": 4.0
  },
  {
    "Id": 10060211,
    "Name": "嬴政-王者守御-近身法术伤害",
    "EffectType": 1,
    "BaseDamage": 200,
    "DamageType": 2,
    "AttackRatio": 0.35,
    "TargetPolicy": 2,
    "Radius": 4.0
  },
  {
    "Id": 10060301,
    "Name": "嬴政-至尊王权-添加剑雨状态",
    "EffectType": 0,
    "BaseDamage": 0,
    "DamageType": 2,
    "AttackRatio": 0,
    "TargetPolicy": 0,
    "Radius": 14.0
  },
  {
    "Id": 10060311,
    "Name": "嬴政-至尊王权-周期飞剑",
    "EffectType": 0,
    "BaseDamage": 0,
    "DamageType": 2,
    "AttackRatio": 0,
    "TargetPolicy": 0,
    "Radius": 14.0
  },
  {
    "Id": 10060313,
    "Name": "嬴政-至尊王权-飞剑命中伤害",
    "EffectType": 1,
    "BaseDamage": 90,
    "DamageType": 2,
    "AttackRatio": 0.08,
    "TargetPolicy": 1,
    "Radius": 0
  }
]
